{
   "Name": "quick_guppy_5496",
   "OnDate": "2025-06-02T21:26:53",
   "Text": "Honestly, I find the endless fan theories about Geralt’s past and the Witcher timeline more confusing than illuminating—sometimes I think the lore gets lost in its own complexity.",
   "Comments": [
      {
         "Name": "cobalt_starfish_2827",
         "OnDate": "2025-06-02T21:37:27",
         "Text": "Sometimes the lore’s richness can be overwhelming, but that’s what makes it so fascinating to unravel."
      }
   ],
   "Likes": [
      "illustrious_hippo_80",
      "cobalt_starfish_2827"
   ]
}